napari_bigwarp/__init__.py
napari_bigwarp/_bigwarp_widget.py
napari_bigwarp/bigwarp.py
napari_bigwarp/_tests/__init__.py
napari_bigwarp/_tests/test_dock_widget.py
napari_bigwarp-0.0.1.dist-info/LICENSE
napari_bigwarp-0.0.1.dist-info/METADATA
napari_bigwarp-0.0.1.dist-info/WHEEL
napari_bigwarp-0.0.1.dist-info/entry_points.txt
napari_bigwarp-0.0.1.dist-info/top_level.txt
napari_bigwarp-0.0.1.dist-info/RECORD
