Metadata-Version: 2.1
Name: napari-bigwarp
Version: 0.0.1
Summary: BigWarp-like interface for napari
Home-page: https://github.com/bkntr/napari-bigwarp
Author: Ben Kantor
Author-email: benkantor@gmail.com
License: BSD-3-Clause
Project-URL: Bug Tracker, https://github.com/bkntr/napari-bigwarp/issues
Project-URL: Documentation, https://github.com/bkntr/napari-bigwarp#README.md
Project-URL: Source Code, https://github.com/bkntr/napari-bigwarp
Project-URL: User Support, https://github.com/bkntr/napari-bigwarp/issues
Platform: UNKNOWN
Classifier: Development Status :: 2 - Pre-Alpha
Classifier: Framework :: napari
Classifier: Intended Audience :: Developers
Classifier: License :: OSI Approved :: BSD License
Classifier: Operating System :: OS Independent
Classifier: Programming Language :: Python
Classifier: Programming Language :: Python :: 3
Classifier: Programming Language :: Python :: 3 :: Only
Classifier: Programming Language :: Python :: 3.7
Classifier: Programming Language :: Python :: 3.8
Classifier: Programming Language :: Python :: 3.9
Classifier: Programming Language :: Python :: 3.10
Classifier: Topic :: Software Development :: Testing
Requires-Python: >=3.7
License-File: LICENSE
Requires-Dist: napari-plugin-engine (>=0.1.4)
Requires-Dist: numpy
Requires-Dist: opencv-contrib-python
Requires-Dist: opencv-python
